{
  "भारत के वर्तमान प्रधानमंत्री कौन हैं?": "नरेंद्र मोदी",
  "भारत के वर्तमान राष्ट्रपति कौन हैं?": "द्रौपदी मुर्मू",
  "भारत की राजधानी क्या है?": "नई दिल्ली",
  "भारत का सबसे बड़ा राज्य क्षेत्रफल के अनुसार कौन सा है?": "राजस्थान",
  "भारत का सबसे छोटा राज्य कौन सा है?": "गोवा",
  "भारत का राष्ट्रीय पशु कौन सा है?": "बाघ",
  "भारत का राष्ट्रीय पक्षी कौन सा है?": "मोर",
  "भारत का राष्ट्रीय फूल कौन सा है?": "कमल",
  "भारत का राष्ट्रीय वृक्ष कौन सा है?": "बरगद",
  "भारत का राष्ट्रीय खेल कौन सा है?": "हॉकी",

  "भारतीय संविधान कब लागू हुआ था?": "26 जनवरी 1950",
  "भारतीय संविधान के निर्माता कौन थे?": "डॉ. भीमराव अंबेडकर",
  "भारत में कुल कितने राज्य हैं?": "28",
  "भारत में कितने केंद्र शासित प्रदेश हैं?": "8",

  "भारत का सबसे ऊँचा पर्वत शिखर कौन सा है?": "कंचनजंगा",
  "भारत की सबसे लंबी नदी कौन सी है?": "गंगा",

  "अजंता की गुफाएँ किस राज्य में हैं?": "महाराष्ट्र",
  "एलोरा की गुफाएँ किस राज्य में स्थित हैं?": "महाराष्ट्र",

  "ताजमहल कहाँ स्थित है?": "आगरा",
  "कोणार्क सूर्य मंदिर किस राज्य में है?": "ओडिशा",
  "सोमनाथ मंदिर किस राज्य में स्थित है?": "गुजरात",
  "राम मंदिर कहाँ स्थित है?": "अयोध्या",

  "भारत का पहला स्वतंत्रता संग्राम कब हुआ था?": "1857",
  "महात्मा गांधी का जन्म कहाँ हुआ था?": "पोरबंदर",

  "भारत के पहले प्रधानमंत्री कौन थे?": "जवाहरलाल नेहरू",
  "भारत की पहली महिला प्रधानमंत्री कौन थीं?": "इंदिरा गांधी",

  "मेक इन इंडिया योजना किससे संबंधित है?": "उद्योग",
  "स्वच्छ भारत अभियान का उद्देश्य क्या है?": "स्वच्छता",
  "डिजिटल इंडिया योजना का उद्देश्य क्या है?": "डिजिटलीकरण",

  "भारत का राष्ट्रीय गीत कौन सा है?": "वंदे मातरम्",
  "भारत का राष्ट्रगान किसने लिखा?": "रवींद्रनाथ टैगोर",

  "भारतीय संसद के कितने सदन हैं?": "दो",
  "लोकसभा के सदस्यों की संख्या कितनी है?": "545",

  "भारत में सर्वोच्च न्यायालय कहाँ स्थित है?": "नई दिल्ली",
  "भारतीय रिज़र्व बैंक का मुख्यालय कहाँ है?": "मुंबई",

  "भारत का सबसे अधिक जनसंख्या वाला राज्य कौन सा है?": "उत्तर प्रदेश"
}